ring/__init__.py
ring/_func_util.py
ring/_memcache.py
ring/chain.py
ring/coder.py
ring/func.py
ring/func_asyncio.py
ring/key.py
ring/util.py
ring-0.2.6.dist-info/DESCRIPTION.rst
ring-0.2.6.dist-info/METADATA
ring-0.2.6.dist-info/RECORD
ring-0.2.6.dist-info/WHEEL
ring-0.2.6.dist-info/metadata.json
ring-0.2.6.dist-info/top_level.txt
